coclico/__init__.py
coclico/_version.py
coclico/example_module.py
coclico/colormaps/slev_div.txt
coclico/utils/__init__.py
coclico/utils/boxes.py
coclico/utils/cloud_services.py
coclico/utils/geo.py
coclico-1.0.1.dist-info/METADATA
coclico-1.0.1.dist-info/WHEEL
coclico-1.0.1.dist-info/licenses/LICENSE
coclico-1.0.1.dist-info/RECORD
